providerkit/.commands.json
providerkit/__init__.py
providerkit/__main__.py
providerkit/cli.py
providerkit/commands/__init__.py
providerkit/commands/provider.py
providerkit/helpers/__init__.py
providerkit/helpers/load.py
providerkit/helpers/module.py
providerkit/kit/__init__.py
providerkit/kit/config.py
providerkit/kit/cost.py
providerkit/kit/package.py
providerkit/kit/response.py
providerkit/kit/service.py
providerkit/kit/urls.py
providerkit/providers/__init__.py
providerkit/providers/config.py
providerkit/providers/folder.py
providerkit/providers/json.py
providerkit/providers/package.py
providerkit/providers/base/__init__.py
providerkit/providers/base/execute.py
providerkit/providers/base/filter.py
providerkit/providers/base/sort.py
providerkit-0.2.4.dist-info/licenses/LICENSE
providerkit-0.2.4.dist-info/METADATA
providerkit-0.2.4.dist-info/WHEEL
providerkit-0.2.4.dist-info/entry_points.txt
providerkit-0.2.4.dist-info/top_level.txt
providerkit-0.2.4.dist-info/RECORD
