Metadata-Version: 2.4
Name: providerkit
Version: 0.2.4
Summary: ProviderKit - Generic provider management library
Author-email: Hicinformatic <hicinformatic@gmail.com>
License: MIT
Project-URL: Homepage, https://github.com/hicinformatic/python-providerkit
Project-URL: Repository, https://github.com/hicinformatic/python-providerkit
Project-URL: Documentation, https://github.com/hicinformatic/python-providerkit#readme
Project-URL: Issues, https://github.com/hicinformatic/python-providerkit/issues
Keywords: provider,service-provider,multi-provider,provider-management,python,abstraction,service-abstraction
Classifier: Development Status :: 4 - Beta
Classifier: Intended Audience :: Developers
Classifier: Programming Language :: Python :: 3
Classifier: Programming Language :: Python :: 3.10
Classifier: Programming Language :: Python :: 3.11
Classifier: Programming Language :: Python :: 3.12
Classifier: Topic :: Software Development :: Libraries :: Python Modules
Classifier: Topic :: Software Development :: Libraries
Requires-Python: >=3.10
License-File: LICENSE
Requires-Dist: qualitybase
Provides-Extra: dev
Provides-Extra: lint
Requires-Dist: qualitybase[lint]; extra == "lint"
Provides-Extra: quality
Requires-Dist: qualitybase[quality]; extra == "quality"
Provides-Extra: security
Requires-Dist: qualitybase[security]; extra == "security"
Provides-Extra: test
Requires-Dist: qualitybase[test]; extra == "test"
Dynamic: license-file
